pyca_blinkstick/__init__.py
pyca_blinkstick/__main__.py
pyca_blinkstick/config.py
pyca_blinkstick/controller.py
pyca_blinkstick/utils.py
tests/__init__.py
tests/test_pyca.py
pyca_blinkstick-0.2.1.dist-info/METADATA
pyca_blinkstick-0.2.1.dist-info/WHEEL
pyca_blinkstick-0.2.1.dist-info/entry_points.txt
pyca_blinkstick-0.2.1.dist-info/top_level.txt
pyca_blinkstick-0.2.1.dist-info/RECORD
