Metadata-Version: 2.1
Name: pyca-blinkstick
Version: 0.2.1
Summary: Blinkstick recording light integration with opencast pyca capture agent
Home-page: https://github.com/mm-dict/pyca-blinkstick
Author: Kristof Keppens
Author-email: kristof.keppens@ugent.be
License: MIT
Platform: UNKNOWN
Requires-Dist: BlinkStick (>=1.2.0)
Requires-Dist: python-dateutil (>=2.4.0)
Requires-Dist: configobj (>=5.0.0)
Requires-Dist: pyusb (>=1.2.1)
Requires-Dist: requests (>=2.26.0)
Requires-Dist: sdnotify (>=0.3.2)
